whylogs/__init__.py
whylogs/api/__init__.py
whylogs/api/annotations.py
whylogs/api/fugue/__init__.py
whylogs/api/fugue/profiler.py
whylogs/api/fugue/registry.py
whylogs/api/logger/__init__.py
whylogs/api/logger/events/__init__.py
whylogs/api/logger/events/event.py
whylogs/api/logger/events/file_name.py
whylogs/api/logger/experimental/logger/__init__.py
whylogs/api/logger/experimental/logger/actor/actor.py
whylogs/api/logger/experimental/logger/actor/data_logger.py
whylogs/api/logger/experimental/logger/actor/faster_fifo_queue_wrapper.py
whylogs/api/logger/experimental/logger/actor/future_util.py
whylogs/api/logger/experimental/logger/actor/list_util.py
whylogs/api/logger/experimental/logger/actor/mp_queue_wrapper.py
whylogs/api/logger/experimental/logger/actor/pipe_signaler.py
whylogs/api/logger/experimental/logger/actor/proc_error_message.py
whylogs/api/logger/experimental/logger/actor/process_actor.py
whylogs/api/logger/experimental/logger/actor/process_rolling_logger.py
whylogs/api/logger/experimental/logger/actor/process_rolling_logger_messages.py
whylogs/api/logger/experimental/logger/actor/signal_util.py
whylogs/api/logger/experimental/logger/actor/string_util.py
whylogs/api/logger/experimental/logger/actor/thread_actor.py
whylogs/api/logger/experimental/logger/actor/thread_rolling_logger.py
whylogs/api/logger/experimental/logger/actor/time_util.py
whylogs/api/logger/logger.py
whylogs/api/logger/result_set.py
whylogs/api/logger/rolling.py
whylogs/api/logger/segment_cache.py
whylogs/api/logger/segment_processing.py
whylogs/api/logger/transient.py
whylogs/api/pyspark/experimental/__init__.py
whylogs/api/pyspark/experimental/profiler.py
whylogs/api/pyspark/experimental/segmented_profiler.py
whylogs/api/reader/__init__.py
whylogs/api/reader/local.py
whylogs/api/reader/reader.py
whylogs/api/reader/s3.py
whylogs/api/store/__init__.py
whylogs/api/store/local_store.py
whylogs/api/store/profile_store.py
whylogs/api/store/query.py
whylogs/api/store/sqlite_store.py
whylogs-1.6.4.dist-info/METADATA
whylogs-1.6.4.dist-info/WHEEL
whylogs-1.6.4.dist-info/RECORD
